[
  {
    "ParameterKey": "ProjectName",
    "ParameterValue": "octopod-backend-api"
  },
  {
    "ParameterKey": "Environment",
    "ParameterValue": "dev"
  },
  {
    "ParameterKey": "GitHubOrgName",
    "ParameterValue": "CoderCouple"
  },
  {
    "ParameterKey": "GitHubRepositoryName",
    "ParameterValue": "octopod-backend"
  },
  {
    "ParameterKey": "ECRRepositoryName",
    "ParameterValue": "octopod-backend-ecr-repo"
  },
  {
    "ParameterKey": "GitHubTokenSecretName",
    "ParameterValue": "OCTOPOD-BACKEND-GITHUB-TOKEN"
  }
]